python_none_objects/__init__.py
python_none_objects/py.typed
python_none_objects-1.1.11.dist-info/METADATA
python_none_objects-1.1.11.dist-info/WHEEL
python_none_objects-1.1.11.dist-info/licenses/COPYING
python_none_objects-1.1.11.dist-info/licenses/COPYING.LESSER
python_none_objects-1.1.11.dist-info/RECORD
