Metadata-Version: 2.3
Name: python-none-objects
Version: 1.1.11
Summary: Add more constant "None" objects to Python to avoid boilerplate code
Project-URL: Homepage, https://github.com/LLyaudet/python-none-objects
Project-URL: Bug Tracker, https://github.com/LLyaudet/python-none-objects/issues
Author-email: Laurent Lyaudet <laurent.lyaudet@gmail.com>
Maintainer-email: Laurent Lyaudet <laurent.lyaudet@gmail.com>
License:                    GNU LESSER GENERAL PUBLIC LICENSE
License-File: COPYING
License-File: COPYING.LESSER
Keywords: Default values,Immutable,None,Python
Classifier: Development Status :: 5 - Production/Stable
Classifier: Intended Audience :: Developers
Classifier: License :: OSI Approved :: GNU Lesser General Public License v3 or later (LGPLv3+)
Classifier: Operating System :: OS Independent
Classifier: Programming Language :: Python
Classifier: Programming Language :: Python :: 3
Classifier: Topic :: Software Development :: Libraries :: Python Modules
Classifier: Typing :: Typed
Requires-Python: >=3.11
Provides-Extra: dev
Requires-Dist: black; extra == 'dev'
Requires-Dist: isort; extra == 'dev'
Requires-Dist: mypy; extra == 'dev'
Requires-Dist: pylint; extra == 'dev'
